longnet/__init__.py
navit/__init__.py
navit-0.0.1.dev0.dist-info/METADATA
navit-0.0.1.dev0.dist-info/WHEEL
navit-0.0.1.dev0.dist-info/top_level.txt
navit-0.0.1.dev0.dist-info/RECORD
